setup.py
chimps/__init__.py
chimps/models.py
chimps/tests.py
chimps/urls.py
chimps/views.py
chimps/__pycache__/__init__.cpython-33.pyc
chimps/locale/fr/LC_MESSAGES/django.mo
chimps/locale/fr/LC_MESSAGES/django.po
chimps/management/__init__.py
chimps/management/commands/__init__.py
chimps/management/commands/chimp_lists.py
chimps/runtests/__init__.py
chimps/runtests/runtests.py
chimps/runtests/settings.py
chimps/runtests/urls.py
chimps/runtests/__pycache__/__init__.cpython-33.pyc
chimps/runtests/__pycache__/runtests.cpython-33.pyc
chimps/templates/chimps/form.html
chimps/templates/chimps/subscribe.html
chimps/templates/chimps/subscribed.html
chimps/templatetags/__init__.py
chimps/templatetags/chimp_tags.py
django_chimps.egg-info/PKG-INFO
django_chimps.egg-info/SOURCES.txt
django_chimps.egg-info/dependency_links.txt
django_chimps.egg-info/requires.txt
django_chimps.egg-info/top_level.txt