Metadata-Version: 1.1
Name: django-chimps
Version: 0.0.4
Summary: Django app to allow users to subscribe to MailChimp lists.
Home-page: http://github.com/simonluijk/django-chimps
Author: Simon Luijk
Author-email: simon@simonluijk.com
License: BSD
Platform: UNKNOWN
Classifier: Development Status :: 4 - Beta
Classifier: Environment :: Web Environment
Classifier: Framework :: Django
Classifier: Intended Audience :: Developers
Classifier: License :: OSI Approved :: BSD License
Classifier: Operating System :: OS Independent
Classifier: Programming Language :: Python
Classifier: Programming Language :: Python :: 3
Classifier: Topic :: Internet :: WWW/HTTP
